timetrix/__init__.py
timetrix/cloocker.py
timetrix/temetnosce.py
timetrix/timetrix.py
timetrix-0.0.10.dist-info/LICENSE
timetrix-0.0.10.dist-info/METADATA
timetrix-0.0.10.dist-info/WHEEL
timetrix-0.0.10.dist-info/top_level.txt
timetrix-0.0.10.dist-info/RECORD
