Metadata-Version: 2.2
Name: timetrix
Version: 0.0.10
Summary: Lightweight and intuitive Python library designed to help developers,track, measure, and visualize time with ease.
Home-page: https://github.com/maglovskiNenad/timetrix
Author: Maglovski Nenad
Author-email: maglovskin@gmail.com
Classifier: Programming Language :: Python :: 3
Classifier: License :: OSI Approved :: MIT License
Classifier: Operating System :: OS Independent
Requires-Python: >=3.6
License-File: LICENSE
Requires-Dist: datetime
Dynamic: author
Dynamic: author-email
Dynamic: classifier
Dynamic: description
Dynamic: description-content-type
Dynamic: home-page
Dynamic: requires-dist
Dynamic: requires-python
Dynamic: summary
